LICENSE.txt
MANIFEST.in
README.md
setup.cfg
setup.py
elitsdk/__init__.py
elitsdk/api.py
elitsdk/benchmark.py
elitsdk/sdk.py
elitsdk/version.py
elitsdk.egg-info/PKG-INFO
elitsdk.egg-info/SOURCES.txt
elitsdk.egg-info/dependency_links.txt
elitsdk.egg-info/top_level.txt
elitsdk/aux/__init__.py
elitsdk/aux/model.py
elitsdk/structure/__init__.py
elitsdk/structure/node.py
tests/__init__.py
tests/api_test.py
tests/sdk_test.py